README
caffeine.py
setup.py
caffeine.egg-info/PKG-INFO
caffeine.egg-info/SOURCES.txt
caffeine.egg-info/dependency_links.txt
caffeine.egg-info/top_level.txt